m269_lib/__init__.py
m269_lib/bag.py
m269_lib/queue.py
m269_lib/stack.py
m269_lib-0.0.2.dist-info/LICENSE
m269_lib-0.0.2.dist-info/METADATA
m269_lib-0.0.2.dist-info/WHEEL
m269_lib-0.0.2.dist-info/RECORD
